jmspy/__init__.py
jmspy/jmspy.py
jmspy/libs/activemq-all-6.1.7.jar
jmspy/libs/jakarta.annotation-api-2.1.1.jar
jmspy/libs/jakarta.jms-api-3.1.0.jar
jmspy/libs/log4j-api-2.25.0.jar
jmspy/libs/log4j-core-2.25.0.jar
jmspy-0.1.1.dist-info/licenses/LICENSE
jmspy-0.1.1.dist-info/METADATA
jmspy-0.1.1.dist-info/WHEEL
jmspy-0.1.1.dist-info/top_level.txt
jmspy-0.1.1.dist-info/RECORD
