Metadata-Version: 2.4
Name: jmspy
Version: 0.1.1
Summary: JPype wrapper to use pure Java JMS to send/receive messages to Apache ActiveMQ broker directly in Python. This is not a STOMP but JVM OpenWire used over JNI.
Author: Tomasz Malewski
License: MIT
Project-URL: Github, https://github.com/Tomasz-Malewski/jmspy
Requires-Python: >=3.8
License-File: LICENSE
Requires-Dist: jpype1
Dynamic: license-file
